sailenv/__init__.py
sailenv/agent.py
sailenv-0.0.2b0.dist-info/LICENSE
sailenv-0.0.2b0.dist-info/METADATA
sailenv-0.0.2b0.dist-info/WHEEL
sailenv-0.0.2b0.dist-info/top_level.txt
sailenv-0.0.2b0.dist-info/RECORD
