Metadata-Version: 2.1
Name: sailenv
Version: 0.0.2b0
Summary: Python API for interfacing with SAILenv
Home-page: https://github.com/sailab-code/SAILenv
Author: Enrico Meloni
Author-email: meloni@diism.unisi.it
License: UNKNOWN
Platform: UNKNOWN
Classifier: Programming Language :: Python :: 3
Classifier: License :: OSI Approved :: MIT License
Classifier: Operating System :: OS Independent
Requires-Python: >=3.6
